{ "tasks" : [
	{"id":"1422075167118","name":"Watch a movie","category":"Recreational","isCompleted":false,"createdAt":"2015-01-24T04:52:47.118Z"},
	{"id":"1422075179581","name":"Fix the bugs","category":"Official","isCompleted":false,"createdAt":"2015-01-24T04:52:59.581Z"},
	{"id":"1422075187303","name":"Prepare the bonus budget","category":"Official","isCompleted":false,"createdAt":"2015-01-24T04:53:07.303Z"},
	{"id":"1422075196353","name":"Renew the passport","category":"Personal","isCompleted":false,"createdAt":"2015-01-24T04:53:16.353Z"},
	{"id":"1422075211433","name":"Hunt for a house","category":"Personal","isCompleted":false,"createdAt":"2015-01-24T04:53:31.433Z"},
	{"id":"1422075223552","name":"Plan for a pub hopping","category":"Recreational","isCompleted":false,"createdAt":"2015-01-24T04:53:43.552Z"}
	]
}